git_guilt/__init__.py
git_guilt/guilt.py
git_guilt-0.33.data/data/man/man1/git-guilt.1
git_guilt-0.33.dist-info/DESCRIPTION.rst
git_guilt-0.33.dist-info/METADATA
git_guilt-0.33.dist-info/RECORD
git_guilt-0.33.dist-info/WHEEL
git_guilt-0.33.dist-info/entry_points.txt
git_guilt-0.33.dist-info/metadata.json
git_guilt-0.33.dist-info/top_level.txt
