Metadata-Version: 2.0
Name: git-guilt
Version: 0.33
Summary: git-guilt provides information on the transfer of ownership in a Git repository
Home-page: https://github.com/mattboyer/git-guilt
Author: Matt Boyer
Author-email: mboyer@sdf.org
License: BSD
Keywords: git blame guilt
Platform: UNKNOWN
Classifier: Environment :: Console
Classifier: Development Status :: 3 - Alpha
Classifier: Intended Audience :: Developers
Classifier: License :: OSI Approved :: BSD License
Classifier: Operating System :: POSIX
Classifier: Topic :: Software Development :: Version Control
Classifier: Programming Language :: Python :: 2.7
Classifier: Programming Language :: Python :: 3.3
Classifier: Programming Language :: Python :: 3.4
Classifier: Programming Language :: Python :: 3.5
Requires-Dist: argparse
